topsis/__init__.py
topsis/topsis.py
Topsis_Udit_102203558-1.0.0.dist-info/METADATA
Topsis_Udit_102203558-1.0.0.dist-info/WHEEL
Topsis_Udit_102203558-1.0.0.dist-info/entry_points.txt
Topsis_Udit_102203558-1.0.0.dist-info/top_level.txt
Topsis_Udit_102203558-1.0.0.dist-info/RECORD
