Metadata-Version: 2.2
Name: Topsis-Udit-102203558
Version: 1.0.0
Summary: A Python package for implementing the TOPSIS method.
Author: Udit Arora
Author-email: uditarora@example.com
Classifier: Programming Language :: Python :: 3
Classifier: License :: OSI Approved :: MIT License
Classifier: Operating System :: OS Independent
Requires-Python: >=3.6
Requires-Dist: numpy
Requires-Dist: pandas
Dynamic: author
Dynamic: author-email
Dynamic: classifier
Dynamic: description
Dynamic: description-content-type
Dynamic: requires-dist
Dynamic: requires-python
Dynamic: summary
